spacyface/__init__.py
spacyface/aligner.py
spacyface/simple_spacy_token.py
spacyface/checker/__init__.py
spacyface/checker/against_corpus.py
spacyface/utils/__init__.py
spacyface/utils/f.py
spacyface/utils/sentence_extracting.py
spacyface-0.3.0.dist-info/aligner/__init__.py
spacyface-0.3.0.dist-info/aligner/aligner.py
spacyface-0.3.0.dist-info/aligner/simple_spacy_token.py
spacyface-0.3.0.dist-info/aligner/__pycache__/__init__.cpython-36.pyc
spacyface-0.3.0.dist-info/aligner/__pycache__/__init__.cpython-37.pyc
spacyface-0.3.0.dist-info/aligner/__pycache__/aligner.cpython-36.pyc
spacyface-0.3.0.dist-info/aligner/__pycache__/aligner.cpython-37.pyc
spacyface-0.3.0.dist-info/aligner/__pycache__/simple_spacy_token.cpython-37.pyc
spacyface-0.3.0.dist-info/aligner/utils/f.py
spacyface-0.3.0.dist-info/aligner/utils/__pycache__/f.cpython-37.pyc
spacyface-0.3.0.dist-info/LICENSE
spacyface-0.3.0.dist-info/METADATA
spacyface-0.3.0.dist-info/WHEEL
spacyface-0.3.0.dist-info/top_level.txt
spacyface-0.3.0.dist-info/RECORD
